area/__init__.py
area/area_determ.py
area/loger.py
areafear-0.0.1.dist-info/METADATA
areafear-0.0.1.dist-info/WHEEL
areafear-0.0.1.dist-info/top_level.txt
areafear-0.0.1.dist-info/RECORD
