Metadata-Version: 2.1
Name: areafear
Version: 0.0.1
Summary: This is the simplest modul for calculate figure area.
Author: karleneg
Author-email: kolya.gar.1@gmail.com
Requires-Python: >=3.11
Requires-Dist: pytest ==8.1.1
Requires-Dist: loguru ==0.7.2
